DELICENSE.txt
LICENSE
MANIFEST.in
README.md
setup.py
site_exceptions_handler/__init__.py
site_exceptions_handler/admin.py
site_exceptions_handler/apps.py
site_exceptions_handler/mixims.py
site_exceptions_handler/models.py
site_exceptions_handler/states.py
site_exceptions_handler/tests.py
site_exceptions_handler/views.py
site_exceptions_handler.egg-info/PKG-INFO
site_exceptions_handler.egg-info/SOURCES.txt
site_exceptions_handler.egg-info/dependency_links.txt
site_exceptions_handler.egg-info/not-zip-safe
site_exceptions_handler.egg-info/requires.txt
site_exceptions_handler.egg-info/top_level.txt
site_exceptions_handler/middleware/GlobalExceptionCatcher.py
site_exceptions_handler/middleware/__init__.py
site_exceptions_handler/migrations/0001_initial.py
site_exceptions_handler/migrations/__init__.py