Metadata-Version: 1.1
Name: site-exceptions-handler
Version: 0.4.4
Summary: Django Site Exception Handler captures and stores the Exceptions into the Database
Home-page: https://bitbucket.org/Matthew-Stuart/user-agent-middleware
Author: Matthew Stuart
Author-email: matthew.stuart@double-eye.com
License: MIT
Platform: any
Classifier: Framework :: Django
Classifier: Framework :: Django :: 1.9
Classifier: Framework :: Django :: 1.10
Classifier: Framework :: Django :: 1.11
Classifier: Environment :: Web Environment
Classifier: Intended Audience :: Developers
Classifier: Intended Audience :: System Administrators
Classifier: License :: OSI Approved :: MIT License
Classifier: Operating System :: OS Independent
Classifier: Programming Language :: Python
Classifier: Programming Language :: Python :: 2.7
Classifier: Programming Language :: Python :: 3
Classifier: Programming Language :: Python :: 3.4
Classifier: Programming Language :: Python :: 3.5
Classifier: Topic :: Software Development
Classifier: Topic :: Software Development :: User Interfaces
Classifier: Topic :: System :: Systems Administration
